ibm_ai_openscale_cli/VERSION
ibm_ai_openscale_cli/__init__.py
ibm_ai_openscale_cli/api_environment.py
ibm_ai_openscale_cli/credentials.py
ibm_ai_openscale_cli/enums.py
ibm_ai_openscale_cli/environments.py
ibm_ai_openscale_cli/main.py
ibm_ai_openscale_cli/openscale_ops.py
ibm_ai_openscale_cli/ops.py
ibm_ai_openscale_cli/reset_ops.py
ibm_ai_openscale_cli/database_classes/cos.py
ibm_ai_openscale_cli/database_classes/db2.py
ibm_ai_openscale_cli/database_classes/postgres.py
ibm_ai_openscale_cli/database_classes/postgres_compose.py
ibm_ai_openscale_cli/database_classes/postgres_icd.py
ibm_ai_openscale_cli/ml_engines/azure_machine_learning.py
ibm_ai_openscale_cli/ml_engines/custom_machine_learning.py
ibm_ai_openscale_cli/ml_engines/sagemaker_machine_learning.py
ibm_ai_openscale_cli/ml_engines/spss_machine_learning.py
ibm_ai_openscale_cli/ml_engines/watson_machine_learning.py
ibm_ai_openscale_cli/models/model.py
ibm_ai_openscale_cli/models/DrugSelectionAutoAIModel/wml/configuration.json
ibm_ai_openscale_cli/models/DrugSelectionAutoAIModel/wml/feedback_data.csv
ibm_ai_openscale_cli/models/DrugSelectionAutoAIModel/wml/history_fairness.json
ibm_ai_openscale_cli/models/DrugSelectionAutoAIModel/wml/history_payloads.json
ibm_ai_openscale_cli/models/DrugSelectionAutoAIModel/wml/history_performance.json
ibm_ai_openscale_cli/models/DrugSelectionAutoAIModel/wml/history_quality.json
ibm_ai_openscale_cli/models/DrugSelectionAutoAIModel/wml/training_data.csv
ibm_ai_openscale_cli/models/DrugSelectionAutoAIModel/wml/training_data_statistics.json
ibm_ai_openscale_cli/models/DrugSelectionAutoAIModel/wml/v4/model_content.gzip
ibm_ai_openscale_cli/models/DrugSelectionAutoAIModel/wml/v4/model_meta.json
ibm_ai_openscale_cli/models/DrugSelectionSparkModel/wml/configuration.json
ibm_ai_openscale_cli/models/DrugSelectionSparkModel/wml/feedback_data.csv
ibm_ai_openscale_cli/models/DrugSelectionSparkModel/wml/history_fairness.json
ibm_ai_openscale_cli-0.2.400.dist-info/LICENSE
ibm_ai_openscale_cli-0.2.400.dist-info/METADATA
ibm_ai_openscale_cli-0.2.400.dist-info/WHEEL
ibm_ai_openscale_cli-0.2.400.dist-info/dependency_links.txt
ibm_ai_openscale_cli-0.2.400.dist-info/entry_points.txt
ibm_ai_openscale_cli-0.2.400.dist-info/top_level.txt
ibm_ai_openscale_cli-0.2.400.dist-info/zip-safe
ibm_ai_openscale_cli-0.2.400.dist-info/RECORD
