Metadata-Version: 2.1
Name: ibm-ai-openscale-cli
Version: 0.2.400
Summary: CLI library to automate the onboarding process to IBM Watson OpenScale
Home-page: https://www.ibm.com/cloud/ai-openscale
Author: IBM Corp
Author-email: wps@us.ibm.com
License: Apache-2.0
Keywords: ai-openscale,ibm-watson
Platform: UNKNOWN
Classifier: Programming Language :: Python
Classifier: Programming Language :: Python :: 3
Classifier: Development Status :: 4 - Beta
Classifier: Intended Audience :: Developers
Classifier: Operating System :: OS Independent
Classifier: Topic :: Software Development :: Libraries :: Python Modules
Classifier: Topic :: Software Development :: Libraries :: Application Frameworks
Requires-Python: >=3.5
Requires-Dist: h5py (==2.9.0)
Requires-Dist: requests (<3.0,>=2.0)
Requires-Dist: urllib3 (==1.24)
Requires-Dist: retry (<1.0.0,>=0.9.0)
Requires-Dist: boto3 (>=1.9.96)
Requires-Dist: psycopg2-binary (==2.7.7)
Requires-Dist: ibm-db (==3.0.1)
Requires-Dist: ibm-ai-openscale (==2.2.1)
Requires-Dist: pandas (==0.24.2)
Requires-Dist: watson-machine-learning-client (==1.0.378)
